dj_tables/__init__.py
dj_tables/mixins.py
dj_tables/templates/dj_tables/bootstrap4.html
dj_tables/templates/dj_tables/bootstrap4_sortlink.html
dj_tables/templatetags/__init__.py
dj_tables/templatetags/dj_tables.py
dj_tables-1.0.0.dist-info/WHEEL
dj_tables-1.0.0.dist-info/METADATA
dj_tables-1.0.0.dist-info/RECORD
