Metadata-Version: 2.1
Name: dj-tables
Version: 1.0.0
Summary: A template only and DRY solution for creating tables.
Home-page: https://github.com/ninjasforhealth/dj-tables
License: UNKNOWN
Author: Zach Perkitny
Author-email: zperkitny@gmail.com
Requires-Python: >=3.6
Requires-Dist: Django>=2.0.0
Project-URL: Documentation, https://dj-tables.readthedocs.io/en/latest/
